kumlog/__init__.py
kumlog/logformat.py
kummis/__init__.py
kummis/logformat.py
kummis-0.0.1.dist-info/DESCRIPTION.rst
kummis-0.0.1.dist-info/METADATA
kummis-0.0.1.dist-info/RECORD
kummis-0.0.1.dist-info/WHEEL
kummis-0.0.1.dist-info/metadata.json
kummis-0.0.1.dist-info/top_level.txt
logformat/__init__.py
logformat/logformat.py
