Metadata-Version: 2.0
Name: kummis
Version: 0.0.1
Summary: Kumparan Log Format
Home-page: https://github.com/jametson/kumlog
Author: Alam Listyadi
Author-email: alam.listyadi@gmail.com
License: BSD 3-Clause License
Platform: UNKNOWN
Classifier: License :: OSI Approved :: BSD License
Classifier: Programming Language :: Python :: 2.6
Classifier: Programming Language :: Python :: 2.7
Classifier: Programming Language :: Python :: 3
Classifier: Programming Language :: Python :: 3.2
Classifier: Programming Language :: Python :: 3.3
Classifier: Programming Language :: Python :: 3.4
Classifier: Programming Language :: Python :: 3.5
